thonny_autosave-0.0.22.dist-info/licenses/LICENSE.txt
thonnycontrib/thonny-autosave/__init__.py
thonny_autosave-0.0.22.dist-info/METADATA
thonny_autosave-0.0.22.dist-info/WHEEL
thonny_autosave-0.0.22.dist-info/entry_points.txt
thonny_autosave-0.0.22.dist-info/top_level.txt
thonny_autosave-0.0.22.dist-info/RECORD
