Metadata-Version: 2.4
Name: thonny-autosave
Version: 0.0.22
Summary: Adds a checkbox to the File menu of Thonny editor, when activated , Automatically saves current file every 10 seconds
Home-page: https://github.com/selmen2004/thonny-autosave
Author: Selmen Arous
Author-email: Selmen Arous <selmen.arous@gmail.com>
License: Copyright (c) 2016 The Python Packaging Authority (PyPA)
Project-URL: Homepage, https://github.com/selmen2004/thonny-autosave
Project-URL: Bug Reports, https://github.com/selmen2004/thonny-autosave/issues
Project-URL: Funding, https://selmen.tn
Project-URL: Say Thanks!, https://selmen.tn
Project-URL: Source, https://github.com/selmen2004/thonny-autosave
Keywords: sample,setuptools,development
Classifier: Development Status :: 3 - Alpha
Classifier: Intended Audience :: Developers
Classifier: Topic :: Software Development :: Build Tools
Classifier: License :: OSI Approved :: MIT License
Classifier: Programming Language :: Python :: 3
Classifier: Programming Language :: Python :: 3.7
Classifier: Programming Language :: Python :: 3.8
Classifier: Programming Language :: Python :: 3.9
Classifier: Programming Language :: Python :: 3.10
Classifier: Programming Language :: Python :: 3.11
Classifier: Programming Language :: Python :: 3 :: Only
Requires-Python: >=3.7
License-File: LICENSE.txt
Requires-Dist: thonny
Dynamic: license-file
